regm.v
/*
 * regm - register memory
 *
 * A 32-bit register memory.  Two registers can be read at once. The
 * variables `read1` and `read2` specify which registers to read.  The
 * output is placed in `data1` and `data2` and at same time one register can
 * be write with wrdata to register specified by wrreg
 *
 */

`ifndef _regm
`define _regm

`ifndef DEBUG_CPU_REG
`define DEBUG_CPU_REG 0
`endif

module regm( write, clk, wrreg, read1, read2, data1, data2, wrdata);

		input   write, clk;
                input   [4:0] wrreg, read1, read2;
                output  [31:0]  data1, data2;
                input   [31:0]  wrdata;

	reg [31:0] mem [0:31];  // 32-bit memory regfile 



	assign data1 = mem[read1];
	assign data2 = mem[read2];

	always @(posedge clk) begin
		if (write ) begin
			mem[wrreg] <= wrdata;
		end
	end
endmodule

`endif

test/regm_test.v
module regm_test;
reg[4:0] read1, read2, wrreg;
reg[31:0] wrdata;
reg write, clk;
wire [31:0] data1, data2;
integer k;

regm test(write, clk, wrreg, read1, read2, data1, data2, wrdata);
initial clk =0;
always #5 clk = !clk;
 
initial
begin $dumpfile("regm_test.vcd");
 $dumpvars(0, regm_test);
#1 write = 0;
end

initial
begin 
#7
for (k=0; k< 32; k=k+1) begin
	wrreg =k ; wrdata = 10*k; write =1;
	#10 write =0; //even the original circuit input is wire kind but here in the test_bench we are giving those inputs as reg to be continuous untill we change.
//call the delay perfectly such that write is high at every posedge by taking
//into consideration that time period of clock is 10
end
 #20
 for(k=0; k<32; k= k+2) begin
	 read1  = k; read2 = k+1;
	 #5;
	 $display("reg[%2d] = %d, reg[%2d] = %d", read1, data1, read2, data2);
 end
 #2000 $finish;
 end 
 endmodule

test/regm_test.vcd
$date
	Sat Oct 21 17:08:58 2023
$end
$version
	Icarus Verilog
$end
$timescale
	1s
$end
$scope module regm_test $end
$var wire 32 ! data2 [31:0] $end
$var wire 32 " data1 [31:0] $end
$var reg 1 # clk $end
$var reg 5 $ read1 [4:0] $end
$var reg 5 % read2 [4:0] $end
$var reg 32 & wrdata [31:0] $end
$var reg 1 ' write $end
$var reg 5 ( wrreg [4:0] $end
$var integer 32 ) k [31:0] $end
$scope module test $end
$var wire 1 # clk $end
$var wire 32 * data1 [31:0] $end
$var wire 32 + data2 [31:0] $end
$var wire 5 , read1 [4:0] $end
$var wire 5 - read2 [4:0] $end
$var wire 32 . wrdata [31:0] $end
$var wire 1 ' write $end
$var wire 5 / wrreg [4:0] $end
$upscope $end
$upscope $end
$enddefinitions $end
$comment Show the parameter values. $end
$dumpall
$end
#0
$dumpvars
bx /
bx .
bx -
bx ,
bx +
bx *
bx )
bx (
x'
bx &
bx %
bx $
0#
bx "
bx !
$end
#1
0'
#5
1#
#7
1'
b0 &
b0 .
b0 (
b0 /
b0 )
#10
0#
#15
1#
#17
b1010 &
b1010 .
b1 (
b1 /
b1 )
1'
#20
0#
#25
1#
#27
b10100 &
b10100 .
b10 (
b10 /
b10 )
1'
#30
0#
#35
1#
#37
b11110 &
b11110 .
b11 (
b11 /
b11 )
1'
#40
0#
#45
1#
#47
b101000 &
b101000 .
b100 (
b100 /
b100 )
1'
#50
0#
#55
1#
#57
b110010 &
b110010 .
b101 (
b101 /
b101 )
1'
#60
0#
#65
1#
#67
b111100 &
b111100 .
b110 (
b110 /
b110 )
1'
#70
0#
#75
1#
#77
b1000110 &
b1000110 .
b111 (
b111 /
b111 )
1'
#80
0#
#85
1#
#87
b1010000 &
b1010000 .
b1000 (
b1000 /
b1000 )
1'
#90
0#
#95
1#
#97
b1011010 &
b1011010 .
b1001 (
b1001 /
b1001 )
1'
#100
0#
#105
1#
#107
b1100100 &
b1100100 .
b1010 (
b1010 /
b1010 )
1'
#110
0#
#115
1#
#117
b1101110 &
b1101110 .
b1011 (
b1011 /
b1011 )
1'
#120
0#
#125
1#
#127
b1111000 &
b1111000 .
b1100 (
b1100 /
b1100 )
1'
#130
0#
#135
1#
#137
b10000010 &
b10000010 .
b1101 (
b1101 /
b1101 )
1'
#140
0#
#145
1#
#147
b10001100 &
b10001100 .
b1110 (
b1110 /
b1110 )
1'
#150
0#
#155
1#
#157
b10010110 &
b10010110 .
b1111 (
b1111 /
b1111 )
1'
#160
0#
#165
1#
#167
b10100000 &
b10100000 .
b10000 (
b10000 /
b10000 )
1'
#170
0#
#175
1#
#177
b10101010 &
b10101010 .
b10001 (
b10001 /
b10001 )
1'
#180
0#
#185
1#
#187
b10110100 &
b10110100 .
b10010 (
b10010 /
b10010 )
1'
#190
0#
#195
1#
#197
b10111110 &
b10111110 .
b10011 (
b10011 /
b10011 )
1'
#200
0#
#205
1#
#207
b11001000 &
b11001000 .
b10100 (
b10100 /
b10100 )
1'
#210
0#
#215
1#
#217
b11010010 &
b11010010 .
b10101 (
b10101 /
b10101 )
1'
#220
0#
#225
1#
#227
b11011100 &
b11011100 .
b10110 (
b10110 /
b10110 )
1'
#230
0#
#235
1#
#237
b11100110 &
b11100110 .
b10111 (
b10111 /
b10111 )
1'
#240
0#
#245
1#
#247
b11110000 &
b11110000 .
b11000 (
b11000 /
b11000 )
1'
#250
0#
#255
1#
#257
b11111010 &
b11111010 .
b11001 (
b11001 /
b11001 )
1'
#260
0#
#265
1#
#267
b100000100 &
b100000100 .
b11010 (
b11010 /
b11010 )
1'
#270
0#
#275
1#
#277
b100001110 &
b100001110 .
b11011 (
b11011 /
b11011 )
1'
#280
0#
#285
1#
#287
b100011000 &
b100011000 .
b11100 (
b11100 /
b11100 )
1'
#290
0#
#295
1#
#297
b100100010 &
b100100010 .
b11101 (
b11101 /
b11101 )
1'
#300
0#
#305
1#
#307
b100101100 &
b100101100 .
b11110 (
b11110 /
b11110 )
1'
#310
0#
#315
1#
#317
b100110110 &
b100110110 .
b11111 (
b11111 /
b11111 )
1'
#320
0#
#325
1#
#327
b100000 )
0'
#330
0#
#335
1#
#340
0#
#345
1#
#347
b1010 !
b1010 +
b1 %
b1 -
b0 "
b0 *
b0 $
b0 ,
b0 )
#350
0#
#352
b11110 !
b11110 +
b11 %
b11 -
b10100 "
b10100 *
b10 $
b10 ,
b10 )
#355
1#
#357
b110010 !
b110010 +
b101 %
b101 -
b101000 "
b101000 *
b100 $
b100 ,
b100 )
#360
0#
#362
b1000110 !
b1000110 +
b111 %
b111 -
b111100 "
b111100 *
b110 $
b110 ,
b110 )
#365
1#
#367
b1011010 !
b1011010 +
b1001 %
b1001 -
b1010000 "
b1010000 *
b1000 $
b1000 ,
b1000 )
#370
0#
#372
b1101110 !
b1101110 +
b1011 %
b1011 -
b1100100 "
b1100100 *
b1010 $
b1010 ,
b1010 )
#375
1#
#377
b10000010 !
b10000010 +
b1101 %
b1101 -
b1111000 "
b1111000 *
b1100 $
b1100 ,
b1100 )
#380
0#
#382
b10010110 !
b10010110 +
b1111 %
b1111 -
b10001100 "
b10001100 *
b1110 $
b1110 ,
b1110 )
#385
1#
#387
b10101010 !
b10101010 +
b10001 %
b10001 -
b10100000 "
b10100000 *
b10000 $
b10000 ,
b10000 )
#390
0#
#392
b10111110 !
b10111110 +
b10011 %
b10011 -
b10110100 "
b10110100 *
b10010 $
b10010 ,
b10010 )
#395
1#
#397
b11010010 !
b11010010 +
b10101 %
b10101 -
b11001000 "
b11001000 *
b10100 $
b10100 ,
b10100 )
#400
0#
#402
b11100110 !
b11100110 +
b10111 %
b10111 -
b11011100 "
b11011100 *
b10110 $
b10110 ,
b10110 )
#405
1#
#407
b11111010 !
b11111010 +
b11001 %
b11001 -
b11110000 "
b11110000 *
b11000 $
b11000 ,
b11000 )
#410
0#
#412
b100001110 !
b100001110 +
b11011 %
b11011 -
b100000100 "
b100000100 *
b11010 $
b11010 ,
b11010 )
#415
1#
#417
b100100010 !
b100100010 +
b11101 %
b11101 -
b100011000 "
b100011000 *
b11100 $
b11100 ,
b11100 )
#420
0#
#422
b100110110 !
b100110110 +
b11111 %
b11111 -
b100101100 "
b100101100 *
b11110 $
b11110 ,
b11110 )
#425
1#
#427
b100000 )
